emfwebcrawler/__init__.py
emfwebcrawler/emfwebcrawler.py
emfwebcrawler-0.3.2.dist-info/LICENSE
emfwebcrawler-0.3.2.dist-info/METADATA
emfwebcrawler-0.3.2.dist-info/WHEEL
emfwebcrawler-0.3.2.dist-info/top_level.txt
emfwebcrawler-0.3.2.dist-info/RECORD
